{"benchmarkResults":{"quarkus-worker-pool":{"avgStartTime":1522.2,"runtimeRunResults":{"10000":{"loadThroughput":10000.0,"responseActualThroughput":9990.43,"responseTimeAvg":1.22,"responseTime50":1.13,"responseTime75":1.59,"responseTime90":1.98,"responseTime99":2.61,"responseTime999":3.05,"responseTime9999":3.37,"responseTime99999":3.81,"responseTimeMax":4.06,"requests":599432.0,"avgRss":466.77249710648147,"minRss":457.84765625,"maxRss":493.7890625,"avgCpu":20.35787037037037,"minCpu":17.5,"maxCpu":81.675},"20000":{"loadThroughput":20000.0,"responseActualThroughput":19979.95,"responseTimeAvg":1.687,"responseTime50":1.59,"responseTime75":2.22,"responseTime90":2.78,"responseTime99":3.72,"responseTime999":4.22,"responseTime9999":4.64,"responseTime99999":5.36,"responseTimeMax":7.884,"requests":1198808.0,"avgRss":474.90596064814815,"minRss":472.78515625,"maxRss":476.63671875,"avgCpu":42.90324074074074,"minCpu":33.325,"maxCpu":44.25},"30000":{"loadThroughput":30000.0,"responseActualThroughput":29852.38,"responseTimeAvg":1.162,"responseTime50":1.12,"responseTime75":1.5,"responseTime90":1.82,"responseTime99":2.39,"responseTime999":3.01,"responseTime9999":4.04,"responseTime99999":5.79,"responseTimeMax":7.18,"requests":1791149.0,"avgRss":485.5104166666667,"minRss":482.7421875,"maxRss":487.82421875,"avgCpu":71.03333333333333,"minCpu":31.675,"maxCpu":73.25},"40000":{"loadThroughput":40000.0,"responseActualThroughput":39959.77,"responseTimeAvg":1.231,"responseTime50":1.18,"responseTime75":1.63,"responseTime90":1.92,"responseTime99":2.47,"responseTime999":3.21,"responseTime9999":4.28,"responseTime99999":6.09,"responseTimeMax":6.664,"requests":2397601.0,"avgRss":498.5333478009259,"minRss":495.625,"maxRss":500.98046875,"avgCpu":83.20787037037037,"minCpu":46.675,"maxCpu":85.25},"50000":{"loadThroughput":50000.0,"responseActualThroughput":49738.26,"responseTimeAvg":14.181,"responseTime50":11.06,"responseTime75":25.55,"responseTime90":33.85,"responseTime99":41.82,"responseTime999":45.95,"responseTime9999":48.99,"responseTime99999":51.36,"responseTimeMax":54.176,"requests":2984263.0,"avgRss":564.9168836805555,"minRss":563.27734375,"maxRss":567.44140625,"avgCpu":98.65925925925927,"minCpu":38.325,"maxCpu":101.75},"60000":{"loadThroughput":60000.0,"responseActualThroughput":59885.88,"responseTimeAvg":26.501,"responseTime50":26.35,"responseTime75":41.22,"responseTime90":49.6,"responseTime99":70.97,"responseTime999":99.84,"responseTime9999":122.05,"responseTime99999":139.39,"responseTimeMax":147.328,"requests":3595173.0,"avgRss":575.1117621527778,"minRss":573.76171875,"maxRss":576.10546875,"avgCpu":99.32592592592593,"minCpu":58.325,"maxCpu":102.25},"65000":{"loadThroughput":65000.0,"responseActualThroughput":64863.39,"responseTimeAvg":35.518,"responseTime50":34.46,"responseTime75":49.44,"responseTime90":60.99,"responseTime99":113.28,"responseTime999":173.82,"responseTime9999":219.01,"responseTime99999":248.32,"responseTimeMax":258.944,"requests":3893881.0,"avgRss":737.1448929398148,"minRss":716.6171875,"maxRss":806.77734375,"avgCpu":99.31666666666668,"minCpu":58.325,"maxCpu":102.25},"68000":{"loadThroughput":68000.0,"responseActualThroughput":67447.43,"responseTimeAvg":92.928,"responseTime50":61.89,"responseTime75":123.33,"responseTime90":205.31,"responseTime99":426.75,"responseTime999":557.57,"responseTime9999":588.8,"responseTime99999":607.74,"responseTimeMax":616.96,"requests":4049355.0,"avgRss":812.4806857638889,"minRss":810.97265625,"maxRss":813.5859375,"avgCpu":99.21435185185184,"minCpu":53.325,"maxCpu":102.0},"70000":{"loadThroughput":70000.0,"responseActualThroughput":68431.49,"responseTimeAvg":750.388,"responseTime50":676.35,"responseTime75":1070.0,"responseTime90":1390.0,"responseTime99":1720.0,"responseTime999":1910.0,"responseTime9999":1950.0,"responseTime99999":1980.0,"responseTimeMax":1988.608,"requests":4108046.0,"avgRss":818.3294994212963,"minRss":817.58203125,"maxRss":819.16796875,"avgCpu":99.39722222222223,"minCpu":61.675,"maxCpu":102.5}}},"quarkus-io-thread":{"avgStartTime":1326.0,"runtimeRunResults":{"10000":{"loadThroughput":10000.0,"responseActualThroughput":9990.37,"responseTimeAvg":1.244,"responseTime50":1.21,"responseTime75":1.63,"responseTime90":1.96,"responseTime99":2.41,"responseTime999":2.83,"responseTime9999":3.16,"responseTime99999":3.46,"responseTimeMax":3.516,"requests":599429.0,"avgRss":465.19675925925924,"minRss":464.92578125,"maxRss":465.3046875,"avgCpu":10.615277777777779,"minCpu":9.5,"maxCpu":31.675},"100000":{"loadThroughput":100000.0,"responseActualThroughput":99114.6,"responseTimeAvg":1.854,"responseTime50":1.37,"responseTime75":2.01,"responseTime90":2.71,"responseTime99":13.84,"responseTime999":22.38,"responseTime9999":28.88,"responseTime99999":31.02,"responseTimeMax":33.504,"requests":5946796.0,"avgRss":476.38368055555554,"minRss":476.078125,"maxRss":476.421875,"avgCpu":95.96712962962964,"minCpu":23.325,"maxCpu":101.0},"110000":{"loadThroughput":110000.0,"responseActualThroughput":109887.9,"responseTimeAvg":2.803,"responseTime50":1.5,"responseTime75":2.29,"responseTime90":7.19,"responseTime99":20.86,"responseTime999":27.26,"responseTime9999":32.48,"responseTime99999":34.4,"responseTimeMax":35.776,"requests":6593182.0,"avgRss":477.37008101851853,"minRss":477.2109375,"maxRss":477.3828125,"avgCpu":97.68425925925925,"minCpu":43.325,"maxCpu":102.0},"120000":{"loadThroughput":120000.0,"responseActualThroughput":119827.79,"responseTimeAvg":9.531,"responseTime50":6.04,"responseTime75":16.43,"responseTime90":23.74,"responseTime99":32.99,"responseTime999":50.88,"responseTime9999":60.96,"responseTime99999":64.1,"responseTimeMax":67.712,"requests":7192151.0,"avgRss":546.8824508101852,"minRss":478.140625,"maxRss":563.19921875,"avgCpu":99.33055555555556,"minCpu":63.325,"maxCpu":102.25},"130000":{"loadThroughput":130000.0,"responseActualThroughput":129849.21,"responseTimeAvg":19.615,"responseTime50":17.5,"responseTime75":27.93,"responseTime90":37.38,"responseTime99":79.42,"responseTime999":134.4,"responseTime9999":180.48,"responseTime99999":190.46,"responseTimeMax":196.992,"requests":7790861.0,"avgRss":564.0716869212963,"minRss":563.47265625,"maxRss":564.1328125,"avgCpu":98.90277777777777,"minCpu":40.0,"maxCpu":104.0},"132000":{"loadThroughput":132000.0,"responseActualThroughput":131688.35,"responseTimeAvg":53.556,"responseTime50":29.65,"responseTime75":55.58,"responseTime90":142.98,"responseTime99":350.72,"responseTime999":456.45,"responseTime9999":483.58,"responseTime99999":495.36,"responseTimeMax":499.2,"requests":7903900.0,"avgRss":665.1690538194445,"minRss":564.2734375,"maxRss":745.453125,"avgCpu":99.07638888888889,"minCpu":46.875,"maxCpu":101.25},"134000":{"loadThroughput":134000.0,"responseActualThroughput":133408.17,"responseTimeAvg":140.288,"responseTime50":85.89,"responseTime75":190.59,"responseTime90":314.62,"responseTime99":713.73,"responseTime999":849.41,"responseTime9999":916.48,"responseTime99999":954.88,"responseTimeMax":963.584,"requests":8004361.0,"avgRss":746.0206886574074,"minRss":745.73046875,"maxRss":746.19921875,"avgCpu":99.2824074074074,"minCpu":60.0,"maxCpu":102.75},"136000":{"loadThroughput":136000.0,"responseActualThroughput":134090.56,"responseTimeAvg":562.07,"responseTime50":386.05,"responseTime75":831.49,"responseTime90":1330.0,"responseTime99":1850.0,"responseTime999":1910.0,"responseTime9999":1950.0,"responseTime99999":1960.0,"responseTimeMax":1961.984,"requests":8045295.0,"avgRss":746.9215856481482,"minRss":746.5,"maxRss":746.984375,"avgCpu":99.17037037037036,"minCpu":51.675,"maxCpu":102.25},"138000":{"loadThroughput":138000.0,"responseActualThroughput":135923.57,"responseTimeAvg":408.248,"responseTime50":395.77,"responseTime75":606.72,"responseTime90":812.03,"responseTime99":1010.0,"responseTime999":1090.0,"responseTime9999":1160.0,"responseTime99999":1180.0,"responseTimeMax":1185.792,"requests":8156233.0,"avgRss":747.7932581018518,"minRss":747.515625,"maxRss":747.828125,"avgCpu":99.22685185185185,"minCpu":56.25,"maxCpu":101.0},"140000":{"loadThroughput":140000.0,"responseActualThroughput":134471.72,"responseTimeAvg":1007.451,"responseTime50":884.22,"responseTime75":1410.0,"responseTime90":1830.0,"responseTime99":2390.0,"responseTime999":2620.0,"responseTime9999":2730.0,"responseTime99999":2760.0,"responseTimeMax":2772.992,"requests":8068159.0,"avgRss":748.4558015046297,"minRss":748.31640625,"maxRss":748.4765625,"avgCpu":98.40601851851852,"minCpu":11.675,"maxCpu":101.25},"20000":{"loadThroughput":20000.0,"responseActualThroughput":19901.46,"responseTimeAvg":1.682,"responseTime50":1.6,"responseTime75":2.16,"responseTime90":2.85,"responseTime99":3.73,"responseTime999":4.17,"responseTime9999":4.52,"responseTime99999":4.87,"responseTimeMax":5.964,"requests":1194134.0,"avgRss":466.82175925925924,"minRss":466.609375,"maxRss":466.875,"avgCpu":21.697222222222223,"minCpu":10.0,"maxCpu":23.0},"30000":{"loadThroughput":30000.0,"responseActualThroughput":29969.99,"responseTimeAvg":1.08,"responseTime50":1.06,"responseTime75":1.44,"responseTime90":1.7,"responseTime99":2.17,"responseTime999":2.72,"responseTime9999":3.14,"responseTime99999":3.88,"responseTimeMax":4.636,"requests":1798195.0,"avgRss":467.91630497685185,"minRss":467.75,"maxRss":467.96484375,"avgCpu":26.60972222222222,"minCpu":25.0,"maxCpu":28.5},"40000":{"loadThroughput":40000.0,"responseActualThroughput":39959.62,"responseTimeAvg":1.221,"responseTime50":1.2,"responseTime75":1.62,"responseTime90":1.89,"responseTime99":2.43,"responseTime999":2.76,"responseTime9999":3.14,"responseTime99999":4.15,"responseTimeMax":4.54,"requests":2397583.0,"avgRss":469.55620659722223,"minRss":468.94921875,"maxRss":469.72265625,"avgCpu":39.61203703703704,"minCpu":33.325,"maxCpu":41.75},"50000":{"loadThroughput":50000.0,"responseActualThroughput":49949.48,"responseTimeAvg":1.079,"responseTime50":1.01,"responseTime75":1.46,"responseTime90":1.78,"responseTime99":2.31,"responseTime999":2.85,"responseTime9999":3.29,"responseTime99999":3.86,"responseTimeMax":4.572,"requests":2996974.0,"avgRss":470.08449074074076,"minRss":469.72265625,"maxRss":470.16015625,"avgCpu":49.12453703703704,"minCpu":26.675,"maxCpu":52.5},"60000":{"loadThroughput":60000.0,"responseActualThroughput":59939.29,"responseTimeAvg":1.157,"responseTime50":1.11,"responseTime75":1.53,"responseTime90":1.87,"responseTime99":2.39,"responseTime999":2.92,"responseTime9999":3.48,"responseTime99999":4.41,"responseTimeMax":5.888,"requests":3596350.0,"avgRss":470.89988425925924,"minRss":470.609375,"maxRss":471.03125,"avgCpu":53.73796296296296,"minCpu":25.0,"maxCpu":55.75},"70000":{"loadThroughput":70000.0,"responseActualThroughput":69928.02,"responseTimeAvg":1.261,"responseTime50":1.2,"responseTime75":1.66,"responseTime90":2.08,"responseTime99":2.58,"responseTime999":3.09,"responseTime9999":3.69,"responseTime99999":5.22,"responseTimeMax":7.364,"requests":4195722.0,"avgRss":472.0691550925926,"minRss":471.6484375,"maxRss":472.15625,"avgCpu":66.68981481481481,"minCpu":31.675,"maxCpu":70.25},"80000":{"loadThroughput":80000.0,"responseActualThroughput":79605.21,"responseTimeAvg":1.29,"responseTime50":1.26,"responseTime75":1.7,"responseTime90":2.11,"responseTime99":2.69,"responseTime999":3.3,"responseTime9999":5.1,"responseTime99999":7.81,"responseTimeMax":9.36,"requests":4776288.0,"avgRss":475.53161168981484,"minRss":472.3125,"maxRss":479.2578125,"avgCpu":79.15648148148148,"minCpu":25.0,"maxCpu":92.25}}}},"graphData":{"quarkus-worker-pool-response-90":[{"key":10000.0,"value":1.98},{"key":20000.0,"value":2.78},{"key":30000.0,"value":1.82},{"key":40000.0,"value":1.92},{"key":50000.0,"value":33.85},{"key":60000.0,"value":49.6},{"key":65000.0,"value":60.99},{"key":68000.0,"value":205.31},{"key":70000.0,"value":1390.0}],"quarkus-io-thread-avgCpu":[{"key":10000.0,"value":10.615277777777779},{"key":20000.0,"value":21.697222222222223},{"key":30000.0,"value":26.60972222222222},{"key":40000.0,"value":39.61203703703704},{"key":50000.0,"value":49.12453703703704},{"key":60000.0,"value":53.73796296296296},{"key":70000.0,"value":66.68981481481481},{"key":80000.0,"value":79.15648148148148},{"key":100000.0,"value":95.96712962962964},{"key":110000.0,"value":97.68425925925925},{"key":120000.0,"value":99.33055555555556},{"key":130000.0,"value":98.90277777777777},{"key":132000.0,"value":99.07638888888889},{"key":134000.0,"value":99.2824074074074},{"key":136000.0,"value":99.17037037037036},{"key":138000.0,"value":99.22685185185185},{"key":140000.0,"value":98.40601851851852}],"quarkus-worker-pool-meanResponse":[{"key":10000.0,"value":1.22},{"key":20000.0,"value":1.687},{"key":30000.0,"value":1.162},{"key":40000.0,"value":1.231},{"key":50000.0,"value":14.181},{"key":60000.0,"value":26.501},{"key":65000.0,"value":35.518},{"key":68000.0,"value":92.928},{"key":70000.0,"value":750.388}],"quarkus-worker-pool-response-50":[{"key":10000.0,"value":1.13},{"key":20000.0,"value":1.59},{"key":30000.0,"value":1.12},{"key":40000.0,"value":1.18},{"key":50000.0,"value":11.06},{"key":60000.0,"value":26.35},{"key":65000.0,"value":34.46},{"key":68000.0,"value":61.89},{"key":70000.0,"value":676.35}],"quarkus-worker-pool-avgCpu":[{"key":10000.0,"value":20.35787037037037},{"key":20000.0,"value":42.90324074074074},{"key":30000.0,"value":71.03333333333333},{"key":40000.0,"value":83.20787037037037},{"key":50000.0,"value":98.65925925925927},{"key":60000.0,"value":99.32592592592593},{"key":65000.0,"value":99.31666666666668},{"key":68000.0,"value":99.21435185185184},{"key":70000.0,"value":99.39722222222223}],"quarkus-io-thread-meanResponse":[{"key":10000.0,"value":1.244},{"key":20000.0,"value":1.682},{"key":30000.0,"value":1.08},{"key":40000.0,"value":1.221},{"key":50000.0,"value":1.079},{"key":60000.0,"value":1.157},{"key":70000.0,"value":1.261},{"key":80000.0,"value":1.29},{"key":100000.0,"value":1.854},{"key":110000.0,"value":2.803},{"key":120000.0,"value":9.531},{"key":130000.0,"value":19.615},{"key":132000.0,"value":53.556},{"key":134000.0,"value":140.288},{"key":136000.0,"value":562.07},{"key":138000.0,"value":408.248},{"key":140000.0,"value":1007.451}],"quarkus-io-thread-response-90":[{"key":10000.0,"value":1.96},{"key":20000.0,"value":2.85},{"key":30000.0,"value":1.7},{"key":40000.0,"value":1.89},{"key":50000.0,"value":1.78},{"key":60000.0,"value":1.87},{"key":70000.0,"value":2.08},{"key":80000.0,"value":2.11},{"key":100000.0,"value":2.71},{"key":110000.0,"value":7.19},{"key":120000.0,"value":23.74},{"key":130000.0,"value":37.38},{"key":132000.0,"value":142.98},{"key":134000.0,"value":314.62},{"key":136000.0,"value":1330.0},{"key":138000.0,"value":812.03},{"key":140000.0,"value":1830.0}],"quarkus-worker-pool-maxResponse":[{"key":10000.0,"value":4.06},{"key":20000.0,"value":7.884},{"key":30000.0,"value":7.18},{"key":40000.0,"value":6.664},{"key":50000.0,"value":54.176},{"key":60000.0,"value":147.328},{"key":65000.0,"value":258.944},{"key":68000.0,"value":616.96},{"key":70000.0,"value":1988.608}],"quarkus-worker-pool-actualTxrate":[{"key":10000.0,"value":9990.43},{"key":20000.0,"value":19979.95},{"key":30000.0,"value":29852.38},{"key":40000.0,"value":39959.77},{"key":50000.0,"value":49738.26},{"key":60000.0,"value":59885.88},{"key":65000.0,"value":64863.39},{"key":68000.0,"value":67447.43},{"key":70000.0,"value":68431.49}],"quarkus-worker-pool-avgRss":[{"key":10000.0,"value":466.77249710648147},{"key":20000.0,"value":474.90596064814815},{"key":30000.0,"value":485.5104166666667},{"key":40000.0,"value":498.5333478009259},{"key":50000.0,"value":564.9168836805555},{"key":60000.0,"value":575.1117621527778},{"key":65000.0,"value":737.1448929398148},{"key":68000.0,"value":812.4806857638889},{"key":70000.0,"value":818.3294994212963}],"quarkus-io-thread-maxResponse":[{"key":10000.0,"value":3.516},{"key":20000.0,"value":5.964},{"key":30000.0,"value":4.636},{"key":40000.0,"value":4.54},{"key":50000.0,"value":4.572},{"key":60000.0,"value":5.888},{"key":70000.0,"value":7.364},{"key":80000.0,"value":9.36},{"key":100000.0,"value":33.504},{"key":110000.0,"value":35.776},{"key":120000.0,"value":67.712},{"key":130000.0,"value":196.992},{"key":132000.0,"value":499.2},{"key":134000.0,"value":963.584},{"key":136000.0,"value":1961.984},{"key":138000.0,"value":1185.792},{"key":140000.0,"value":2772.992}],"quarkus-worker-pool-response-99999":[{"key":10000.0,"value":3.81},{"key":20000.0,"value":5.36},{"key":30000.0,"value":5.79},{"key":40000.0,"value":6.09},{"key":50000.0,"value":51.36},{"key":60000.0,"value":139.39},{"key":65000.0,"value":248.32},{"key":68000.0,"value":607.74},{"key":70000.0,"value":1980.0}],"quarkus-io-thread-response-99999":[{"key":10000.0,"value":3.46},{"key":20000.0,"value":4.87},{"key":30000.0,"value":3.88},{"key":40000.0,"value":4.15},{"key":50000.0,"value":3.86},{"key":60000.0,"value":4.41},{"key":70000.0,"value":5.22},{"key":80000.0,"value":7.81},{"key":100000.0,"value":31.02},{"key":110000.0,"value":34.4},{"key":120000.0,"value":64.1},{"key":130000.0,"value":190.46},{"key":132000.0,"value":495.36},{"key":134000.0,"value":954.88},{"key":136000.0,"value":1960.0},{"key":138000.0,"value":1180.0},{"key":140000.0,"value":2760.0}],"quarkus-worker-pool-response-99":[{"key":10000.0,"value":2.61},{"key":20000.0,"value":3.72},{"key":30000.0,"value":2.39},{"key":40000.0,"value":2.47},{"key":50000.0,"value":41.82},{"key":60000.0,"value":70.97},{"key":65000.0,"value":113.28},{"key":68000.0,"value":426.75},{"key":70000.0,"value":1720.0}],"quarkus-io-thread-actualTxrate":[{"key":10000.0,"value":9990.37},{"key":20000.0,"value":19901.46},{"key":30000.0,"value":29969.99},{"key":40000.0,"value":39959.62},{"key":50000.0,"value":49949.48},{"key":60000.0,"value":59939.29},{"key":70000.0,"value":69928.02},{"key":80000.0,"value":79605.21},{"key":100000.0,"value":99114.6},{"key":110000.0,"value":109887.9},{"key":120000.0,"value":119827.79},{"key":130000.0,"value":129849.21},{"key":132000.0,"value":131688.35},{"key":134000.0,"value":133408.17},{"key":136000.0,"value":134090.56},{"key":138000.0,"value":135923.57},{"key":140000.0,"value":134471.72}],"quarkus-io-thread-response-50":[{"key":10000.0,"value":1.21},{"key":20000.0,"value":1.6},{"key":30000.0,"value":1.06},{"key":40000.0,"value":1.2},{"key":50000.0,"value":1.01},{"key":60000.0,"value":1.11},{"key":70000.0,"value":1.2},{"key":80000.0,"value":1.26},{"key":100000.0,"value":1.37},{"key":110000.0,"value":1.5},{"key":120000.0,"value":6.04},{"key":130000.0,"value":17.5},{"key":132000.0,"value":29.65},{"key":134000.0,"value":85.89},{"key":136000.0,"value":386.05},{"key":138000.0,"value":395.77},{"key":140000.0,"value":884.22}],"quarkus-io-thread-response-99":[{"key":10000.0,"value":2.41},{"key":20000.0,"value":3.73},{"key":30000.0,"value":2.17},{"key":40000.0,"value":2.43},{"key":50000.0,"value":2.31},{"key":60000.0,"value":2.39},{"key":70000.0,"value":2.58},{"key":80000.0,"value":2.69},{"key":100000.0,"value":13.84},{"key":110000.0,"value":20.86},{"key":120000.0,"value":32.99},{"key":130000.0,"value":79.42},{"key":132000.0,"value":350.72},{"key":134000.0,"value":713.73},{"key":136000.0,"value":1850.0},{"key":138000.0,"value":1010.0},{"key":140000.0,"value":2390.0}],"quarkus-io-thread-avgRss":[{"key":10000.0,"value":465.19675925925924},{"key":20000.0,"value":466.82175925925924},{"key":30000.0,"value":467.91630497685185},{"key":40000.0,"value":469.55620659722223},{"key":50000.0,"value":470.08449074074076},{"key":60000.0,"value":470.89988425925924},{"key":70000.0,"value":472.0691550925926},{"key":80000.0,"value":475.53161168981484},{"key":100000.0,"value":476.38368055555554},{"key":110000.0,"value":477.37008101851853},{"key":120000.0,"value":546.8824508101852},{"key":130000.0,"value":564.0716869212963},{"key":132000.0,"value":665.1690538194445},{"key":134000.0,"value":746.0206886574074},{"key":136000.0,"value":746.9215856481482},{"key":138000.0,"value":747.7932581018518},{"key":140000.0,"value":748.4558015046297}]}}